directory/__init__.py
directory/urls.py
directory/views.py
django_directory-0.0.3.dist-info/METADATA
django_directory-0.0.3.dist-info/WHEEL
django_directory-0.0.3.dist-info/top_level.txt
django_directory-0.0.3.dist-info/RECORD
