Metadata-Version: 2.1
Name: django-directory
Version: 0.0.3
Summary: A Django application to list and download files from a directory
Home-page: https://github.com/ASKBOT/django-directory
Author: Evgeny.Fadeev
Author-email: evgeny.fadeev@gmail.com
License: GPLv3
Keywords: django,list,download,files,directory
Platform: UNKNOWN
Classifier: Development Status :: 4 - Beta
Classifier: Environment :: Web Environment
Classifier: Framework :: Django
Classifier: Intended Audience :: Developers
Classifier: License :: OSI Approved :: GNU General Public License (GPL)
Classifier: Natural Language :: English
Classifier: Operating System :: OS Independent
Classifier: Programming Language :: Python :: 2.7
Classifier: Topic :: Internet :: WWW/HTTP :: WSGI :: Application
Requires-Dist: Django (>=1.11.16)
